odoo/addons/l10n_ch_invoice_reports/README.rst
odoo/addons/l10n_ch_invoice_reports/__init__.py
odoo/addons/l10n_ch_invoice_reports/__manifest__.py
odoo/addons/l10n_ch_invoice_reports/controllers/__init__.py
odoo/addons/l10n_ch_invoice_reports/controllers/portal.py
odoo/addons/l10n_ch_invoice_reports/data/reports.xml
odoo/addons/l10n_ch_invoice_reports/i18n/de.po
odoo/addons/l10n_ch_invoice_reports/i18n/fr.po
odoo/addons/l10n_ch_invoice_reports/i18n/it.po
odoo/addons/l10n_ch_invoice_reports/i18n/l10n_ch_invoice_reports.pot
odoo/addons/l10n_ch_invoice_reports/models/__init__.py
odoo/addons/l10n_ch_invoice_reports/models/account_invoice.py
odoo/addons/l10n_ch_invoice_reports/models/mail_template.py
odoo/addons/l10n_ch_invoice_reports/models/report.py
odoo/addons/l10n_ch_invoice_reports/models/res_company.py
odoo/addons/l10n_ch_invoice_reports/models/res_config_settings.py
odoo/addons/l10n_ch_invoice_reports/readme/CONTRIBUTORS.rst
odoo/addons/l10n_ch_invoice_reports/readme/CREDITS.rst
odoo/addons/l10n_ch_invoice_reports/readme/DESCRIPTION.rst
odoo/addons/l10n_ch_invoice_reports/readme/USAGE.rst
odoo/addons/l10n_ch_invoice_reports/static/description/icon.png
odoo/addons/l10n_ch_invoice_reports/static/description/index.html
odoo/addons/l10n_ch_invoice_reports/views/res_config_settings.xml
odoo_addon_l10n_ch_invoice_reports-15.0.1.0.0.8.dist-info/METADATA
odoo_addon_l10n_ch_invoice_reports-15.0.1.0.0.8.dist-info/WHEEL
odoo_addon_l10n_ch_invoice_reports-15.0.1.0.0.8.dist-info/top_level.txt
odoo_addon_l10n_ch_invoice_reports-15.0.1.0.0.8.dist-info/RECORD
